audiosegment.py
algorithms/__init__.py
algorithms/asa.py
algorithms/eventdetection.py
algorithms/filters.py
algorithms/util.py
audiosegment-0.23.0.dist-info/LICENSE.txt
audiosegment-0.23.0.dist-info/METADATA
audiosegment-0.23.0.dist-info/WHEEL
audiosegment-0.23.0.dist-info/top_level.txt
audiosegment-0.23.0.dist-info/RECORD
