Metadata-Version: 2.1
Name: audiosegment
Version: 0.23.0
Summary: Wrapper for pydub.AudioSegment for additional methods.
Home-page: https://github.com/MaxStrange/AudioSegment
Author: Max Strange
Author-email: maxfieldstrange@gmail.com
License: MIT
Keywords: audio sound pydub
Platform: UNKNOWN
Classifier: Development Status :: 3 - Alpha
Classifier: Intended Audience :: Developers
Classifier: License :: OSI Approved :: MIT License
Classifier: Operating System :: OS Independent
Classifier: Programming Language :: Python
Classifier: Programming Language :: Python :: 3
Classifier: Programming Language :: Python :: 3.4
Classifier: Programming Language :: Python :: 3.5
Classifier: Programming Language :: Python :: 3.6
Classifier: Programming Language :: Python :: 3.7
Classifier: Programming Language :: Python :: 3.8
Classifier: Topic :: Multimedia :: Sound/Audio
Classifier: Topic :: Multimedia :: Sound/Audio :: Analysis
Classifier: Topic :: Software Development :: Libraries
Classifier: Topic :: Utilities
Requires-Python: ~=3.4
Provides-Extra: Optimizations
Provides-Extra: Mel Frequencies
